netrun/testing/__init__.py
netrun/testing/api_clients.py
netrun/testing/async_utils.py
netrun/testing/auth.py
netrun/testing/database.py
netrun/testing/environment.py
netrun/testing/filesystem.py
netrun/testing/logging.py
netrun/testing/py.typed
netrun/testing/redis.py
netrun_pytest_fixtures/__init__.py
netrun_pytest_fixtures/api_clients.py
netrun_pytest_fixtures/async_utils.py
netrun_pytest_fixtures/auth.py
netrun_pytest_fixtures/database.py
netrun_pytest_fixtures/environment.py
netrun_pytest_fixtures/filesystem.py
netrun_pytest_fixtures/logging.py
netrun_pytest_fixtures/redis.py
netrun_pytest_fixtures-2.1.0.dist-info/METADATA
netrun_pytest_fixtures-2.1.0.dist-info/WHEEL
netrun_pytest_fixtures-2.1.0.dist-info/entry_points.txt
netrun_pytest_fixtures-2.1.0.dist-info/licenses/LICENSE
netrun_pytest_fixtures-2.1.0.dist-info/RECORD
