Metadata-Version: 2.4
Name: netrun-pytest-fixtures
Version: 2.1.0
Summary: Unified pytest fixtures for Netrun Systems services - eliminates 71% fixture duplication
Project-URL: Homepage, https://netrunsystems.com
Project-URL: Repository, https://github.com/netrunsystems/netrun-pytest-fixtures
Project-URL: Documentation, https://github.com/netrunsystems/netrun-pytest-fixtures/blob/main/README.md
Project-URL: Changelog, https://github.com/netrunsystems/netrun-pytest-fixtures/blob/main/CHANGELOG.md
Author-email: Netrun Systems <engineering@netrunsystems.com>
Maintainer-email: Netrun Systems <engineering@netrunsystems.com>
License: MIT
License-File: LICENSE
Keywords: async,fastapi,fixtures,netrun,pytest,redis,sqlalchemy,testing
Classifier: Development Status :: 5 - Production/Stable
Classifier: Framework :: Pytest
Classifier: Intended Audience :: Developers
Classifier: License :: OSI Approved :: MIT License
Classifier: Operating System :: OS Independent
Classifier: Programming Language :: Python :: 3
Classifier: Programming Language :: Python :: 3.10
Classifier: Programming Language :: Python :: 3.11
Classifier: Programming Language :: Python :: 3.12
Classifier: Topic :: Software Development :: Libraries :: Python Modules
Classifier: Topic :: Software Development :: Testing
Classifier: Typing :: Typed
Requires-Python: >=3.10
Requires-Dist: cryptography>=41.0.0
Requires-Dist: netrun-core>=2.0.0
Requires-Dist: pytest-asyncio>=0.21.0
Requires-Dist: pytest>=7.0.0
Provides-Extra: all
Requires-Dist: aiosqlite>=0.19.0; extra == 'all'
Requires-Dist: fastapi>=0.100.0; extra == 'all'
Requires-Dist: httpx>=0.24.0; extra == 'all'
Requires-Dist: netrun-logging>=2.0.0; extra == 'all'
Requires-Dist: pyyaml>=6.0.0; extra == 'all'
Requires-Dist: redis>=4.6.0; extra == 'all'
Requires-Dist: sqlalchemy[asyncio]>=2.0.0; extra == 'all'
Provides-Extra: dev
Requires-Dist: black>=23.0.0; extra == 'dev'
Requires-Dist: mypy>=1.5.0; extra == 'dev'
Requires-Dist: netrun-logging>=2.0.0; extra == 'dev'
Requires-Dist: pytest-cov>=4.1.0; extra == 'dev'
Requires-Dist: ruff>=0.1.0; extra == 'dev'
Provides-Extra: fastapi
Requires-Dist: fastapi>=0.100.0; extra == 'fastapi'
Provides-Extra: httpx
Requires-Dist: httpx>=0.24.0; extra == 'httpx'
Provides-Extra: logging
Requires-Dist: netrun-logging>=2.0.0; extra == 'logging'
Provides-Extra: redis
Requires-Dist: redis>=4.6.0; extra == 'redis'
Provides-Extra: sqlalchemy
Requires-Dist: aiosqlite>=0.19.0; extra == 'sqlalchemy'
Requires-Dist: sqlalchemy[asyncio]>=2.0.0; extra == 'sqlalchemy'
Provides-Extra: yaml
Requires-Dist: pyyaml>=6.0.0; extra == 'yaml'
